{
  "name": {
    "active": true,
    "authentication_method": "cleartext",
    "password": "1234",
    "authenticated": false,
    "roles": []
  },
  "sam": {
    "active": true,
    "authentication_method": "cleartext",
    "password": "1234",
    "authenticated": true,
    "roles": []
  },
  "ben": {
    "active": true,
    "authentication_method": "cleartext",
    "password": "1234",
    "authenticated": true,
    "roles": []
  },
  "alex": {
    "active": true,
    "authentication_method": "cleartext",
    "password": "1234",
    "authenticated": true,
    "roles": []
  },
  "xander": {
    "active": true,
    "authentication_method": "cleartext",
    "password": "1234",
    "authenticated": true,
    "roles": []
  },
  "triet": {
    "active": true,
    "authentication_method": "cleartext",
    "password": "1234",
    "authenticated": false,
    "roles": []
  },
  "khue": {
    "active": true,
    "roles": [],
    "authentication_method": "cleartext",
    "authenticated": false,
    "password": "1234"
  }
}